{
    "description": "",
    "tags": [],
    "size": {
        "height": 533,
        "width": 799
    },
    "objects": [
        {
            "id": 700806203,
            "classId": 2908318,
            "description": "",
            "geometryType": "rectangle",
            "labelerLogin": "beifa",
            "createdAt": "2021-04-27T19:58:32.767Z",
            "updatedAt": "2021-04-27T19:58:32.767Z",
            "tags": [],
            "classTitle": "toucan",
            "points": {
                "exterior": [
                    [
                        242,
                        170
                    ],
                    [
                        549,
                        461
                    ]
                ],
                "interior": []
            }
        }
    ]
}