{
    "description": "",
    "tags": [],
    "size": {
        "height": 532,
        "width": 800
    },
    "objects": [
        {
            "id": 700800120,
            "classId": 2908318,
            "description": "",
            "geometryType": "rectangle",
            "labelerLogin": "beifa",
            "createdAt": "2021-04-27T17:39:30.779Z",
            "updatedAt": "2021-04-27T17:39:30.779Z",
            "tags": [],
            "classTitle": "toucan",
            "points": {
                "exterior": [
                    [
                        136,
                        118
                    ],
                    [
                        484,
                        482
                    ]
                ],
                "interior": []
            }
        }
    ]
}